cook/__init__.py
cook/__main__.py
cook/actions.py
cook/contexts.py
cook/controller.py
cook/manager.py
cook/task.py
cook/util.py
cook_build-0.7.3.dist-info/licenses/LICENSE
cook_build-0.7.3.dist-info/METADATA
cook_build-0.7.3.dist-info/WHEEL
cook_build-0.7.3.dist-info/entry_points.txt
cook_build-0.7.3.dist-info/top_level.txt
cook_build-0.7.3.dist-info/RECORD
