Metadata-Version: 2.4
Name: cook-build
Version: 0.7.3
Summary: A task-centric build system with simple declarative recipes specified in Python
Author: Till Hoffmann
License: BSD-3-Clause
Project-URL: Homepage, https://github.com/tillahoffmann/cook-build
Project-URL: Documentation, https://github.com/tillahoffmann/cook-build
Project-URL: Repository, https://github.com/tillahoffmann/cook-build
Project-URL: Issues, https://github.com/tillahoffmann/cook-build/issues
Classifier: Development Status :: 4 - Beta
Classifier: Intended Audience :: Developers
Classifier: License :: OSI Approved :: BSD License
Classifier: Operating System :: OS Independent
Classifier: Programming Language :: Python :: 3
Classifier: Programming Language :: Python :: 3.10
Classifier: Programming Language :: Python :: 3.11
Classifier: Programming Language :: Python :: 3.12
Classifier: Programming Language :: Python :: 3.13
Classifier: Topic :: Software Development :: Build Tools
Classifier: Topic :: System :: Software Distribution
Classifier: Typing :: Typed
Requires-Python: >=3.10
License-File: LICENSE
Requires-Dist: colorama>=0.4.6
Requires-Dist: networkx>=3.2.1
Dynamic: license-file
